mpl_poormans_3d/__init__.py
mpl_poormans_3d/_version.py
mpl_poormans_3d/bezier_helper.py
mpl_poormans_3d/example.py
mpl_poormans_3d/poormans_3d.py
mpl_poormans_3d/poormans_3d_helper.py
mpl_poormans_3d/prism_3d.py
mpl_poormans_3d/shadow.py
mpl_poormans_3d/text_path.py
mpl_poormans_3d/tests/__init__.py
mpl_poormans_3d/tests/test_example.py
mpl_poormans_3d-0.1.0.dist-info/LICENSE
mpl_poormans_3d-0.1.0.dist-info/METADATA
mpl_poormans_3d-0.1.0.dist-info/WHEEL
mpl_poormans_3d-0.1.0.dist-info/top_level.txt
mpl_poormans_3d-0.1.0.dist-info/RECORD
